setup.py
prove/__init__.py
prove.egg-info/PKG-INFO
prove.egg-info/SOURCES.txt
prove.egg-info/dependency_links.txt
prove.egg-info/requires.txt
prove.egg-info/top_level.txt