Metadata-Version: 1.1
Name: prove
Version: 0.0.1
Summary: Prove API client
Home-page: https://github.com/getprove/prove-python
Author: Nick Baugh
Author-email: niftylettuce@gmail.com
License: UNKNOWN
Keywords: prove
Platform: UNKNOWN
Classifier: Development Status :: 5 - Production/Stable
Classifier: Intended Audience :: Developers
Classifier: License :: OSI Approved :: MIT License
Classifier: Operating System :: OS Independent
Classifier: Programming Language :: Python
Classifier: Programming Language :: Python :: 2.5
Classifier: Programming Language :: Python :: 2.6
Classifier: Programming Language :: Python :: 2.7
Classifier: Programming Language :: Python :: 3.2
Classifier: Topic :: Software Development :: Libraries :: Python Modules
Classifier: Topic :: Communications :: Telephony
